spakky/plugins/rabbitmq/__init__.py
spakky/plugins/rabbitmq/common/__init__.py
spakky/plugins/rabbitmq/common/config.py
spakky/plugins/rabbitmq/common/constants.py
spakky/plugins/rabbitmq/event/__init__.py
spakky/plugins/rabbitmq/event/consumer.py
spakky/plugins/rabbitmq/event/publisher.py
spakky/plugins/rabbitmq/main.py
spakky/plugins/rabbitmq/post_processor.py
spakky/plugins/rabbitmq/py.typed
spakky_rabbitmq-5.0.1.dist-info/WHEEL
spakky_rabbitmq-5.0.1.dist-info/entry_points.txt
spakky_rabbitmq-5.0.1.dist-info/METADATA
spakky_rabbitmq-5.0.1.dist-info/RECORD
