Metadata-Version: 2.3
Name: spakky-rabbitmq
Version: 5.0.1
Summary: RabbitMQ plugin for Spakky framework
Author: Spakky
Author-email: Spakky <sejong418@icloud.com>
License: MIT
Requires-Dist: aio-pika>=9.5.8
Requires-Dist: pika>=1.3.2
Requires-Dist: pika-stubs>=0.1.3
Requires-Dist: pydantic>=2.12.5
Requires-Dist: pydantic-settings>=2.12.0
Requires-Dist: spakky-event>=5.0.1
Requires-Python: >=3.11
